[
{
    "id":"dssdfs",
    "image":"/images/beer1.png",
    "name":"麒麟淡麗啤酒(罐裝)(24入)",
    "En_name":"Kirin Green Label Beer",
    "price":1200,
    "currency":"NT$",
    "describe":"擁有芳香啤酒花獨特香氣以及清爽暢悅的口感。",
    "country":"日本",
    "brand":"Kirin",
    "ml":"500ml",
    "percent":"4.5%",
    "countInStock": 10  
},
{
    "id":"dssddfsffs",
    "image":"/images/beer2.png",
    "name":"西班牙金星啤酒(12入)",
    "En_name":"Estrerlla Damm Inedit Beer",
    "price":1000,
    "currency":"NT$",
    "describe":"米其林三星首選佐餐啤酒，獲世界冠軍啤酒金獎的頂級「香檳啤酒」！",
    "country":"西班牙",
    "brand":"Estrella Damm",
    "ml":"750ml",
    "percent":"4.8%",
    "countInStock": 5
},
{
    "id":"dsfdfd",
    "image":"/images/beer3.png",
    "name":"健力士黑生啤酒(24入)",
    "En_name":"Guinness Draught in Can",
    "price":1500,
    "currency":"NT$",
    "describe":"全球銷售第一品牌黑啤酒，在台銷售第一黑啤酒。",
    "country":"愛爾蘭",
    "brand":"Guinness",
    "ml":"440ml",
    "percent":"4.2%",
    "countInStock": 2
},
{
    "id":"dssdffs",
    "image":"/images/beer4.png",
    "name":"ORION啤酒(瓶裝)(12入)",
    "En_name":"Orion Draft Beer",
    "price":1700,
    "currency":"NT$",
    "describe":"帶有清新青草及餅乾淡淡麥芽香氣，些許的柑橘香氣，酒體輕爽，苦味不明顯，相當地清新好喝。",
    "country":"日本",
    "brand":"Orion",
    "ml":"500ml",
    "percent":"5%",
    "countInStock": 10  
},
{
    "id":"dsfdgsrfb",
    "image":"/images/beer8.png",
    "name":"麒麟一番榨啤酒(瓶裝)(12入)",
    "En_name":"Kirin Beer",
    "price":3200,
    "currency":"NT$",
    "describe":"日本原裝進口的「KIRIN一番搾」啤酒，只萃取第一道麥汁的甘醇口感。",
    "country":"日本",
    "brand":"Kirin",
    "ml":"330ml",
    "percent":"5%",
    "countInStock": 18  
},
{
    "id":"dBDdfd",
    "image":"/images/beer7.png",
    "name":"朝日啤酒(瓶裝)(12入)",
    "En_name":"Asahi Super Dry Beer",
    "price":1900,
    "currency":"NT$",
    "describe":"Japan’s No.1 Beer“辛口KARAKUCHI”",
    "country":"日本",
    "brand":"Asahi",
    "ml":"633ml",
    "percent":"4.5%",
    "countInStock": 7
},
{
    "id":"dFBDGERd",
    "image":"/images/beer6.png",
    "name":"雷柯德水果酒 草莓萊姆(24入)",
    "En_name":"Rekorderlig Strawberry-Lime Cider",
    "price":2000,
    "currency":"NT$",
    "describe":"全球首創草莓萊姆風味，配上薄荷葉和檸檬片，創造出豐富且難忘的味蕾享受！",
    "country":"瑞典",
    "brand":"AB ÅBRO BRYGGERI",
    "ml":"330ml",
    "percent":"4.5%",
    "countInStock": 4
}
,{
    "id":"dDFFFf",
    "image":"/images/beer5.png",
    "name":"海尼根啤酒(瓶裝)(12入)",
    "En_name":"Heineken Beer",
    "price":900,
    "currency":"NT$",
    "describe":"濃郁飽滿經典拉格風味：經典海尼根有著濃郁飽滿大麥香氣、與細緻果香。",
    "country":"荷蘭",
    "brand":"Heineken",
    "ml":"330ml",
    "percent":"5%",
    "countInStock": 20
}

]